django_view_manager/__init__.py
django_view_manager/utils/__init__.py
django_view_manager/utils/apps.py
django_view_manager/utils/management/__init__.py
django_view_manager/utils/management/commands/__init__.py
django_view_manager/utils/management/commands/makeviewmigration.py
django_view_manager-2.0.0.dist-info/licenses/LICENSE
django_view_manager-2.0.0.dist-info/METADATA
django_view_manager-2.0.0.dist-info/WHEEL
django_view_manager-2.0.0.dist-info/top_level.txt
django_view_manager-2.0.0.dist-info/RECORD
