Metadata-Version: 2.4
Name: django-view-manager
Version: 2.0.0
Summary: A management command for django that provides diffs of sql views.
Author-email: Arrai Innovations <support@arrai.com>
Project-URL: Repository, https://github.com/arrai-innovations/django-view-manager/
Classifier: Development Status :: 4 - Beta
Classifier: Programming Language :: Python :: 3
Classifier: Programming Language :: Python :: 3.9
Classifier: Programming Language :: Python :: 3.10
Classifier: Programming Language :: Python :: 3.11
Classifier: Programming Language :: Python :: 3.12
Classifier: Programming Language :: Python :: 3.13
Classifier: Programming Language :: Python :: 3.14
Classifier: License :: OSI Approved :: BSD License
Classifier: Environment :: Console
Classifier: Framework :: Django
Classifier: Intended Audience :: Developers
Classifier: Topic :: Utilities
Requires-Python: >=3.9
License-File: LICENSE
Requires-Dist: django>=4.2.0
Dynamic: license-file
